[
  {
    "id":1,
    "countries":"India",
    "LI_inMillions":623.7230055,
    "cows_inMillions":43.717,
    "Consumption":80.4
  },
  {
    "id":2,
    "countries":"United States of America",
    "LI_inMillions":112.2197875,
    "cows_inMillions":9.198,
    "Consumption":256.8
  },
  {
    "id":3,
    "countries":"China",
    "LI_inMillions":1236.5996,
    "cows_inMillions":12.297297,
    "Consumption":31.5
  },
  {
    "id":4,
    "countries":"Pakistan",
    "LI_inMillions":104.2017888,
    "cows_inMillions":10.493,
    "Consumption":178.6
  },
  {
    "id":5,
    "countries":"Brazil",
    "LI_inMillions":170.4399464,
    "cows_inMillions":23.229193,
    "Consumption":150.8
  },
  {
    "id":6,
    "countries":"Russian Federation",
    "LI_inMillions":18.58491284,
    "cows_inMillions":8.136896,
    "Consumption":173.9
  },
  {
    "id":7,
    "countries":"Germany",
    "LI_inMillions":12.26965095,
    "cows_inMillions":4.190103,
    "Consumption":255.4
  },
  {
    "id":8,
    "countries":"France",
    "LI_inMillions":13.0685552,
    "cows_inMillions":5.619569,
    "Consumption":250
  },
  {
    "id":9,
    "countries":"New Zealand",
    "LI_inMillions":0.39456,
    "cows_inMillions":4.528736,
    "Consumption":149.3
  },
  {
    "id":10,
    "countries":"Turkey",
    "LI_inMillions":51.97155412,
    "cows_inMillions":4.761142,
    "Consumption":165.8
  },
  {
    "id":11,
    "countries":"United Kingdom",
    "LI_inMillions":10.12142688,
    "cows_inMillions":0,
    "Consumption":241
  },
  {
    "id":12,
    "countries":"Poland",
    "LI_inMillions":14.08340435,
    "cows_inMillions":0,
    "Consumption":197.9
  },
  {
    "id":13,
    "countries":"Argentina",
    "LI_inMillions":24.9933696,
    "cows_inMillions":0,
    "Consumption":193.8
  },
  {
    "id":14,
    "countries":"Mexico",
    "LI_inMillions":79.44107886,
    "cows_inMillions":0,
    "Consumption":111.2
  },
  {
    "id":15,
    "countries":"Australia",
    "LI_inMillions":1.1170012,
    "cows_inMillions":0,
    "Consumption":229.9
  },
  {
    "id":16,
    "countries":"Canada",
    "LI_inMillions":6.868556,
    "cows_inMillions":0,
    "Consumption":218.4
  },
  {
    "id":17,
    "countries":"Spain",
    "LI_inMillions":11.21824728,
    "cows_inMillions":0,
    "Consumption":179.8
  },
  {
    "id":18,
    "countries":"Sudan (former)",
    "LI_inMillions":22.1509158,
    "cows_inMillions":0,
    "Consumption":170.4
  },
  {
    "id":19,
    "countries":"Japan",
    "LI_inMillions":125.2609315,
    "cows_inMillions":0.9996,
    "Consumption":71.3
  },
  {
    "id":20,
    "countries":"Iran (Islamic Republic of)",
    "LI_inMillions":45.1105932,
    "cows_inMillions":0,
    "Consumption":59.5
  }
]